MANIFEST.in
README.txt
setup.py
docs/HISTORY.txt
src/zeam/__init__.py
src/zeam.form.viewlet.egg-info/PKG-INFO
src/zeam.form.viewlet.egg-info/SOURCES.txt
src/zeam.form.viewlet.egg-info/dependency_links.txt
src/zeam.form.viewlet.egg-info/namespace_packages.txt
src/zeam.form.viewlet.egg-info/not-zip-safe
src/zeam.form.viewlet.egg-info/requires.txt
src/zeam.form.viewlet.egg-info/top_level.txt
src/zeam/form/__init__.py
src/zeam/form/viewlet/__init__.py
src/zeam/form/viewlet/configure.zcml
src/zeam/form/viewlet/form.py
src/zeam/form/viewlet/ftesting.zcml
src/zeam/form/viewlet/interfaces.py
src/zeam/form/viewlet/meta.py
src/zeam/form/viewlet/testing.py
src/zeam/form/viewlet/default_templates/formtemplate.cpt
src/zeam/form/viewlet/ftests/__init__.py
src/zeam/form/viewlet/ftests/test_form.py
src/zeam/form/viewlet/ftests/forms/__init__.py
src/zeam/form/viewlet/ftests/forms/viewlet.py
src/zeam/form/viewlet/ftests/forms/viewletmanager.py
src/zeam/form/viewlet/ftests/forms/viewlet_templates/index.cpt
src/zeam/form/viewlet/ftests/forms/viewletmanager_templates/index.cpt