Metadata-Version: 1.0
Name: zeam.form.viewlet
Version: 1.2
Summary: zeam.form forms in a viewlet
Home-page: http://pypi.python.org/pypi/zeam.form.viewlet
Author: Sylvain Viollon
Author-email: thefunny@gmail.com
License: BSD
Keywords: zeam form viewlet
Platform: UNKNOWN
Classifier: Programming Language :: Python
Classifier: Topic :: Software Development :: Libraries :: Python Modules
